AUTHORS
LICENSE-CeCILL.txt
LICENSE.txt
MANIFEST.in
README.md
setup.cfg
setup.py
test/test_sequencing_summary_extractor.py
toulligqc/__init__.py
toulligqc/bam_extractor.py
toulligqc/common.py
toulligqc/common_statistics.py
toulligqc/configuration.py
toulligqc/extractor_common.py
toulligqc/fast5_extractor.py
toulligqc/fastq_bam_common.py
toulligqc/fastq_extractor.py
toulligqc/html_report_generator.py
toulligqc/plotly_graph_common.py
toulligqc/plotly_graph_generator.py
toulligqc/plotly_graph_onedsquare_generator.py
toulligqc/pod5_extractor.py
toulligqc/report_data_file_generator.py
toulligqc/sequencing_summary_extractor.py
toulligqc/sequencing_summary_onedsquare_extractor.py
toulligqc/sequencing_telemetry_extractor.py
toulligqc/toulligqc.py
toulligqc/toulligqc_info_extractor.py
toulligqc/version.py
toulligqc.egg-info/PKG-INFO
toulligqc.egg-info/SOURCES.txt
toulligqc.egg-info/dependency_links.txt
toulligqc.egg-info/entry_points.txt
toulligqc.egg-info/not-zip-safe
toulligqc.egg-info/requires.txt
toulligqc.egg-info/top_level.txt
toulligqc/resources/plotly-latest.min.js
toulligqc/resources/toulligqc.css
toulligqc/resources/toulligqc.png