Metadata-Version: 2.1
Name: toulligqc
Version: 2.7.1
Summary: A post sequencing QC tool for Oxford Nanopore sequencers
Home-page: https://github.com/GenomiqueENS/toulligQC
Author: Genomic Paris Centre team
Author-email: toulligqc@bio.ens.psl.eu
License: GPL V3
Keywords: Nanopore MinION QC report
Platform: ALL
Classifier: Development Status :: 5 - Production/Stable
Classifier: Environment :: Console
Classifier: Operating System :: POSIX
Classifier: Intended Audience :: Science/Research
Classifier: Topic :: Scientific/Engineering :: Bio-Informatics
Classifier: License :: OSI Approved :: GNU General Public License v3 (GPLv3)
Classifier: License :: OSI Approved :: CEA CNRS Inria Logiciel Libre License, version 2.1 (CeCILL-2.1)
Classifier: Programming Language :: Python :: 3.12
Requires-Python: >=3.11.0
License-File: LICENSE-CeCILL.txt
License-File: LICENSE.txt
License-File: AUTHORS
